{"version":1,"generatedAt":"2025-11-03T18:27:50.846Z","updatedAt":"2025-11-03T22:46:58.399Z","meetInfo":{"meetName":"2025 FAST December Open","dates":"December 13th 2025 - December 14th 2025","location":"Florida Aquatics Swimming & Training - 4635 SW 67th Ave. Rd Ocala, FL, 34474","entryLimits":"Swimmers will be limited to 4 events per day.","awards":"Ribbons for 8 & Under, 9-10, 11-12, 13 & Over. Places 1st-10th.","sessionDetails":[{"session":"Saturday AM (11 & Over)","warmUp":"9:30 AM","startTime":"10:30 AM"},{"session":"Saturday PM (10 & Under)","warmUp":"Immediately following conclusion of morning session","startTime":"30 minutes after the conclusion of the 400 IMs"},{"session":"Sunday AM (All Ages)","warmUp":"9:30 AM","startTime":"10:30 AM"}]},"events":[{"eventNumber":"1","ageGroup":"11 & Over","distance":200,"stroke":"Freestyle Relay","day":"Saturday AM","originalDescription":"11 & Over 200 Freestyle Relay","gender":"Girls"},{"eventNumber":"2","ageGroup":"11 & Over","distance":200,"stroke":"Freestyle Relay","day":"Saturday AM","originalDescription":"11 & Over 200 Freestyle Relay","gender":"Boys"},{"eventNumber":"3","ageGroup":"11 & Over","distance":100,"stroke":"Individual Medley","day":"Saturday AM","originalDescription":"11 & Over 100 IM","gender":"Girls"},{"eventNumber":"4","ageGroup":"11 & Over","distance":100,"stroke":"Individual Medley","day":"Saturday AM","originalDescription":"11 & Over 100 IM","gender":"Boys"},{"eventNumber":"5","ageGroup":"11 & Over","distance":50,"stroke":"Backstroke","day":"Saturday AM","originalDescription":"11 & Over 50 Backstroke","gender":"Girls"},{"eventNumber":"6","ageGroup":"11 & Over","distance":50,"stroke":"Backstroke","day":"Saturday AM","originalDescription":"11 & Over 50 Backstroke","gender":"Boys"},{"eventNumber":"7","ageGroup":"11 & Over","distance":100,"stroke":"Butterfly","day":"Saturday AM","originalDescription":"11 & Over 100 Butterfly","gender":"Girls"},{"eventNumber":"8","ageGroup":"11 & Over","distance":100,"stroke":"Butterfly","day":"Saturday AM","originalDescription":"11 & Over 100 Butterfly","gender":"Boys"},{"eventNumber":"9","ageGroup":"11 & Over","distance":200,"stroke":"Breaststroke","day":"Saturday AM","originalDescription":"11 & Over 200 Breaststroke","gender":"Girls"},{"eventNumber":"10","ageGroup":"11 & Over","distance":200,"stroke":"Breaststroke","day":"Saturday AM","originalDescription":"11 & Over 200 Breaststroke","gender":"Boys"},{"eventNumber":"11","ageGroup":"11 & Over","distance":100,"stroke":"Freestyle","day":"Saturday AM","originalDescription":"11 & Over 100 Freestyle","gender":"Girls"},{"eventNumber":"12","ageGroup":"11 & Over","distance":100,"stroke":"Freestyle","day":"Saturday AM","originalDescription":"11 & Over 100 Freestyle","gender":"Boys"},{"eventNumber":"13","ageGroup":"11 & Over","distance":200,"stroke":"Backstroke","day":"Saturday AM","originalDescription":"11 & Over 200 Backstroke","gender":"Girls"},{"eventNumber":"14","ageGroup":"11 & Over","distance":200,"stroke":"Backstroke","day":"Saturday AM","originalDescription":"11 & Over 200 Backstroke","gender":"Boys"},{"eventNumber":"15","ageGroup":"11 & Over","distance":50,"stroke":"Breaststroke","day":"Saturday AM","originalDescription":"11 & Over 50 Breaststroke","gender":"Girls"},{"eventNumber":"16","ageGroup":"11 & Over","distance":50,"stroke":"Breaststroke","day":"Saturday AM","originalDescription":"11 & Over 50 Breaststroke","gender":"Boys"},{"eventNumber":"17","ageGroup":"11 & Over","distance":400,"stroke":"Individual Medley","day":"Saturday AM","originalDescription":"11 & Over 400 IM","gender":"Girls"},{"eventNumber":"18","ageGroup":"11 & Over","distance":400,"stroke":"Individual Medley","day":"Saturday AM","originalDescription":"11 & Over 400 IM","gender":"Boys"},{"eventNumber":"19","ageGroup":"10 & Under","distance":200,"stroke":"Freestyle Relay","day":"Saturday PM","originalDescription":"10 & Under 200 Freestyle Relay","gender":"Girls"},{"eventNumber":"20","ageGroup":"10 & Under","distance":200,"stroke":"Freestyle Relay","day":"Saturday PM","originalDescription":"10 & Under 200 Freestyle Relay","gender":"Boys"},{"eventNumber":"21","ageGroup":"10 & Under","distance":100,"stroke":"Freestyle","day":"Saturday PM","originalDescription":"10 & Under 100 Freestyle","gender":"Girls"},{"eventNumber":"22","ageGroup":"10 & Under","distance":100,"stroke":"Freestyle","day":"Saturday PM","originalDescription":"10 & Under 100 Freestyle","gender":"Boys"},{"eventNumber":"23","ageGroup":"10 & Under","distance":25,"stroke":"Butterfly","day":"Saturday PM","originalDescription":"10 & Under 25 Butterfly","gender":"Girls"},{"eventNumber":"24","ageGroup":"10 & Under","distance":25,"stroke":"Butterfly","day":"Saturday PM","originalDescription":"10 & Under 25 Butterfly","gender":"Boys"},{"eventNumber":"25","ageGroup":"10 & Under","distance":50,"stroke":"Butterfly","day":"Saturday PM","originalDescription":"10 & Under 50 Butterfly","gender":"Girls"},{"eventNumber":"26","ageGroup":"10 & Under","distance":50,"stroke":"Butterfly","day":"Saturday PM","originalDescription":"10 & Under 50 Butterfly","gender":"Boys"},{"eventNumber":"27","ageGroup":"10 & Under","distance":25,"stroke":"Backstroke","day":"Saturday PM","originalDescription":"10 & Under 25 Backstroke","gender":"Girls"},{"eventNumber":"28","ageGroup":"10 & Under","distance":25,"stroke":"Backstroke","day":"Saturday PM","originalDescription":"10 & Under 25 Backstroke","gender":"Boys"},{"eventNumber":"29","ageGroup":"10 & Under","distance":50,"stroke":"Backstroke","day":"Saturday PM","originalDescription":"10 & Under 50 Backstroke","gender":"Girls"},{"eventNumber":"30","ageGroup":"10 & Under","distance":50,"stroke":"Backstroke","day":"Saturday PM","originalDescription":"10 & Under 50 Backstroke","gender":"Boys"},{"eventNumber":"31","ageGroup":"10 & Under","distance":25,"stroke":"Breaststroke","day":"Saturday PM","originalDescription":"10 & Under 25 Breaststroke","gender":"Girls"},{"eventNumber":"32","ageGroup":"10 & Under","distance":25,"stroke":"Breaststroke","day":"Saturday PM","originalDescription":"10 & Under 25 Breaststroke","gender":"Boys"},{"eventNumber":"33","ageGroup":"10 & Under","distance":50,"stroke":"Breaststroke","day":"Saturday PM","originalDescription":"10 & Under 50 Breaststroke","gender":"Girls"},{"eventNumber":"34","ageGroup":"10 & Under","distance":50,"stroke":"Breaststroke","day":"Saturday PM","originalDescription":"10 & Under 50 Breaststroke","gender":"Boys"},{"eventNumber":"35","ageGroup":"10 & Under","distance":25,"stroke":"Freestyle","day":"Saturday PM","originalDescription":"10 & Under 25 Freestyle","gender":"Girls"},{"eventNumber":"36","ageGroup":"10 & Under","distance":25,"stroke":"Freestyle","day":"Saturday PM","originalDescription":"10 & Under 25 Freestyle","gender":"Boys"},{"eventNumber":"37","ageGroup":"10 & Under","distance":50,"stroke":"Freestyle","day":"Saturday PM","originalDescription":"10 & Under 50 Freestyle","gender":"Girls"},{"eventNumber":"38","ageGroup":"10 & Under","distance":50,"stroke":"Freestyle","day":"Saturday PM","originalDescription":"10 & Under 50 Freestyle","gender":"Boys"},{"eventNumber":"39","ageGroup":"10 & Under","distance":100,"stroke":"Individual Medley","day":"Saturday PM","originalDescription":"10 & Under 100 IM","gender":"Girls"},{"eventNumber":"40","ageGroup":"10 & Under","distance":100,"stroke":"Individual Medley","day":"Saturday PM","originalDescription":"10 & Under 100 IM","gender":"Boys"},{"eventNumber":"41","ageGroup":"Open","distance":200,"stroke":"Medley Relay","day":"Sunday AM","originalDescription":"Open 200 Medley Relay","gender":"Girls"},{"eventNumber":"42","ageGroup":"Open","distance":200,"stroke":"Medley Relay","day":"Sunday AM","originalDescription":"Open 200 Medley Relay","gender":"Boys"},{"eventNumber":"43","ageGroup":"Open","distance":200,"stroke":"Individual Medley","day":"Sunday AM","originalDescription":"Open 200 IM","gender":"Girls"},{"eventNumber":"44","ageGroup":"Open","distance":200,"stroke":"Individual Medley","day":"Sunday AM","originalDescription":"Open 200 IM","gender":"Boys"},{"eventNumber":"45","ageGroup":"Open","distance":50,"stroke":"Butterfly","day":"Sunday AM","originalDescription":"Open 50 Butterfly","gender":"Girls"},{"eventNumber":"46","ageGroup":"Open","distance":50,"stroke":"Butterfly","day":"Sunday AM","originalDescription":"Open 50 Butterfly","gender":"Boys"},{"eventNumber":"47","ageGroup":"Open","distance":200,"stroke":"Freestyle","day":"Sunday AM","originalDescription":"Open 200 Freestyle","gender":"Girls"},{"eventNumber":"48","ageGroup":"Open","distance":200,"stroke":"Freestyle","day":"Sunday AM","originalDescription":"Open 200 Freestyle","gender":"Boys"},{"eventNumber":"49","ageGroup":"Open","distance":100,"stroke":"Breaststroke","day":"Sunday AM","originalDescription":"Open 100 Breaststroke","gender":"Girls"},{"eventNumber":"50","ageGroup":"Open","distance":100,"stroke":"Breaststroke","day":"Sunday AM","originalDescription":"Open 100 Breaststroke","gender":"Boys"},{"eventNumber":"51","ageGroup":"Open","distance":200,"stroke":"Butterfly","day":"Sunday AM","originalDescription":"Open 200 Butterfly","gender":"Girls"},{"eventNumber":"52","ageGroup":"Open","distance":200,"stroke":"Butterfly","day":"Sunday AM","originalDescription":"Open 200 Butterfly","gender":"Boys"},{"eventNumber":"53","ageGroup":"Open","distance":100,"stroke":"Backstroke","day":"Sunday AM","originalDescription":"Open 100 Backstroke","gender":"Girls"},{"eventNumber":"54","ageGroup":"Open","distance":100,"stroke":"Backstroke","day":"Sunday AM","originalDescription":"Open 100 Backstroke","gender":"Boys"},{"eventNumber":"55","ageGroup":"Open","distance":50,"stroke":"Freestyle","day":"Sunday AM","originalDescription":"Open 50 Freestyle","gender":"Girls"},{"eventNumber":"56","ageGroup":"Open","distance":50,"stroke":"Freestyle","day":"Sunday AM","originalDescription":"Open 50 Freestyle","gender":"Boys"},{"eventNumber":"57","ageGroup":"Open","distance":500,"stroke":"Freestyle","day":"Sunday AM","originalDescription":"Open 500 Free","gender":"Girls"},{"eventNumber":"58","ageGroup":"Open","distance":500,"stroke":"Freestyle","day":"Sunday AM","originalDescription":"Open 500 Free","gender":"Boys"}],"status":"published"}